[
  {
    "title": "7/22(화) '서비스 오류에 대한 보상 상자' 지급 안내",
    "date": "2025.07.22",
    "link": "https://mabinogi.nexon.com/page/news/notice_view.asp?id=4892906"
  },
  {
    "title": "[완료/점검보상] 7/22(화) 정식 서버 긴급 점검 안내 (10:30~16:00)",
    "date": "2025.07.21",
    "link": "https://mabinogi.nexon.com/page/news/notice_view.asp?id=4892905"
  },
  {
    "title": "(내용추가3) 7/21(월) 캐릭터명 경매장 이용 불가 안내",
    "date": "2025.07.21",
    "link": "https://mabinogi.nexon.com/page/news/notice_view.asp?id=4892904"
  }
]