[
  {
    "title": "6/26(금) 운영정책 위반 단속 결과 안내",
    "date": "2026.06.26",
    "link": "https://mabinogi.nexon.com/page/news/notice_view.asp?id=4893610"
  },
  {
    "title": "프라이빗 아이 박스",
    "date": "2026.06.25",
    "link": "https://mabinogi.nexon.com/page/news/notice_view.asp?id=4893596"
  },
  {
    "title": "2026년 7월 캐릭터 서버 이전, 낭만 농장/달빛 섬 이름 변경 서비스 진행일 안내",
    "date": "2026.06.25",
    "link": "https://mabinogi.nexon.com/page/news/notice_view.asp?id=4893601"
  },
  {
    "title": "6/25(목) 마비노기 버그 신고 포상 지급 안내",
    "date": "2026.06.25",
    "link": "https://mabinogi.nexon.com/page/news/notice_view.asp?id=4893593"
  }
]